{
  "formatVersion": 1,
  "generatedAt": "2026-06-08T15:23:13.080543+00:00",
  "platforms": [
    {
      "uid": "net.minecraft",
      "name": "Mojang",
      "sha256": "905f33084c31fd4b95524105efa5a09d92ee2778f902be05ac580f02ec2984b7",
      "url": "net.minecraft/package.json"
    },
    {
      "uid": "io.papermc.paper",
      "name": "Paper",
      "sha256": "298547d21f83c79fc1a54861a33f4758c1d5eb6cb851c8e447e95685830c9112",
      "url": "io.papermc.paper/package.json"
    },
    {
      "uid": "build.purpurmc.purpur",
      "name": "Purpur",
      "sha256": "224fe19e0d5c7f72f1c886b697eeb0efcc65e1056e79b9389f25660b6db3d940",
      "url": "build.purpurmc.purpur/package.json"
    },
    {
      "uid": "net.neoforged",
      "name": "NeoForge",
      "sha256": "8da117d87f9ed831fb5b48aa3cc350822d66a4202da04f9c7c9c9093a93ce1d7",
      "url": "net.neoforged/package.json"
    },
    {
      "uid": "net.fabricmc.fabric",
      "name": "Fabric",
      "sha256": "8aab93fcba130e7657c0212e7e2c6682a9a728e95ffc12d6d2b194d4bbf34a62",
      "url": "net.fabricmc.fabric/package.json"
    },
    {
      "uid": "net.minecraft.java",
      "name": "Java Runtimes",
      "sha256": "986684b2ff7c772b1176a347e3df7fcd7424753af66723a4e25d6c773a598c5b",
      "url": "net.minecraft.java/package.json"
    },
    {
      "uid": "net.adoptium.java",
      "name": "Java Runtimes",
      "sha256": "adf949b183cafcf6c6e9b9370b465a42a9e1ae439944f1c79645cff861e4c2b6",
      "url": "net.adoptium.java/package.json"
    },
    {
      "uid": "net.minecraftforge",
      "name": "Forge",
      "sha256": "04de5d22d175cb6ebe37ae96b898abcb3edd77a66bdd57751a4c159d85a7bf8f",
      "url": "net.minecraftforge/package.json"
    }
  ]
}